BybitWebsocket/__init__.py
bybit_ws-0.1.8.dist-info/METADATA
bybit_ws-0.1.8.dist-info/WHEEL
bybit_ws-0.1.8.dist-info/top_level.txt
bybit_ws-0.1.8.dist-info/RECORD
