Metadata-Version: 1.0
Name: bybit-ws
Version: 0.1.8
Summary: bybit websocket client
Home-page: https://github.com/bybit-exchange/api-connectors/tree/master/official-ws/python
Author: Simon
Author-email: simon.zhang@bybit.com
License: UNKNOWN
Platform: UNKNOWN
